randomGenjnp/__init__.py
randomGenjnp/mod.py
randomGenjnp-2.0.0.dist-info/LICENSE
randomGenjnp-2.0.0.dist-info/METADATA
randomGenjnp-2.0.0.dist-info/WHEEL
randomGenjnp-2.0.0.dist-info/top_level.txt
randomGenjnp-2.0.0.dist-info/RECORD
