Metadata-Version: 2.1
Name: randomGenjnp
Version: 2.0.0
Summary: This is a package created for random generating JSON, Numbers and passwords
Home-page: https://github.com/varunkatiyar819/randomGenjnp
Author: Varun Katiyar
Author-email: varunkatiyar819@gmail.com
License: UNKNOWN
Platform: UNKNOWN
License-File: LICENSE
